mmpos/__init__.py
mmpos/api/__init__.py
mmpos/api/farms.py
mmpos/api/profiles.py
mmpos/api/rigs.py
mmpos/api/utils.py
mmpos/cli/__init__.py
mmpos/cli/cli.py
mmpos/cli/farms/__init__.py
mmpos/cli/farms/commands.py
mmpos/cli/profiles/__init__.py
mmpos/cli/profiles/commands.py
mmpos/cli/rigs/__init__.py
mmpos/cli/rigs/commands.py
mmpos-0.2.3.dist-info/METADATA
mmpos-0.2.3.dist-info/WHEEL
mmpos-0.2.3.dist-info/entry_points.txt
mmpos-0.2.3.dist-info/top_level.txt
mmpos-0.2.3.dist-info/RECORD
